phylotree/__init__.py
phylotree/pytree.cpython-311-x86_64-linux-gnu.so
phylotree-0.1.1.data/data/LICENSE
phylotree-0.1.1.dist-info/LICENSE
phylotree-0.1.1.dist-info/METADATA
phylotree-0.1.1.dist-info/WHEEL
phylotree-0.1.1.dist-info/top_level.txt
phylotree-0.1.1.dist-info/RECORD
