Metadata-Version: 2.1
Name: phylotree
Version: 0.1.1
Summary: A Rust backed package to deal with phylogenetic trees
Author: Luc Blassel
License: GPL3
Project-URL: Bug Tracker, https://github.com/lucblassel/phylotree-rs/issues
Project-URL: Documentation, https://github.com/lucblassel/phylotree-rs
Project-URL: Source Code, https://github.com/lucblassel/phylotree-rs
Keywords: phylogenetic tree distance matrix
Classifier: Development Status :: 3 - Alpha
Classifier: Intended Audience :: Science/Research
Classifier: License :: OSI Approved :: GNU General Public License v3 (GPLv3)
Classifier: Natural Language :: English
Classifier: Operating System :: OS Independent
Classifier: Programming Language :: Python :: 3.7
Classifier: Programming Language :: Python :: 3.8
Classifier: Programming Language :: Python :: 3.9
Classifier: Programming Language :: Python :: 3.10
Classifier: Programming Language :: Python :: 3.11
Classifier: Programming Language :: Rust
Classifier: Topic :: Scientific/Engineering :: Bio-Informatics
Requires-Python: >=3.7
License-File: LICENSE
